odoo/addons/shopinvader_payment_manual/README.rst
odoo/addons/shopinvader_payment_manual/__init__.py
odoo/addons/shopinvader_payment_manual/__manifest__.py
odoo/addons/shopinvader_payment_manual/components/__init__.py
odoo/addons/shopinvader_payment_manual/components/payment_transaction_event_listerner.py
odoo/addons/shopinvader_payment_manual/demo/payment_demo.xml
odoo/addons/shopinvader_payment_manual/i18n/shopinvader_payment_manual.pot
odoo/addons/shopinvader_payment_manual/readme/CONTRIBUTORS.rst
odoo/addons/shopinvader_payment_manual/readme/DESCRIPTION.rst
odoo/addons/shopinvader_payment_manual/services/__init__.py
odoo/addons/shopinvader_payment_manual/services/payment_manual.py
odoo/addons/shopinvader_payment_manual/static/description/index.html
odoo/addons/shopinvader_payment_manual/tests/__init__.py
odoo/addons/shopinvader_payment_manual/tests/test_payment_manual.py
odoo13_addon_shopinvader_payment_manual-13.0.1.0.1.dev4.dist-info/METADATA
odoo13_addon_shopinvader_payment_manual-13.0.1.0.1.dev4.dist-info/WHEEL
odoo13_addon_shopinvader_payment_manual-13.0.1.0.1.dev4.dist-info/top_level.txt
odoo13_addon_shopinvader_payment_manual-13.0.1.0.1.dev4.dist-info/RECORD
