Metadata-Version: 2.1
Name: odoo13-addon-shopinvader_payment_manual
Version: 13.0.1.0.1.dev4
Summary: REST Services for manual payment (like bank transfer, check...)
Home-page: https://github.com/shopinvader/odoo-shopinvader-payment
Author: ACSONE SA/NV
License: AGPL-3
Classifier: Programming Language :: Python
Classifier: Framework :: Odoo
Classifier: Framework :: Odoo :: 13.0
Classifier: License :: OSI Approved :: GNU Affero General Public License v3
Requires-Python: >=3.5
Requires-Dist: odoo13-addon-invader-payment-manual
Requires-Dist: odoo13-addon-shopinvader-payment
Requires-Dist: odoo <13.1dev,>=13.0a
